rastless/__init__.py
rastless/cli/__init__.py
rastless/cli/colormaps.py
rastless/cli/layers.py
rastless/cli/management.py
rastless/cli/permissions.py
rastless/cli/validate.py
rastless/commands/__init__.py
rastless/commands/colormaps.py
rastless/commands/layers.py
rastless/commands/permissions.py
rastless/commands/validate.py
rastless/config.py
rastless/core/__init__.py
rastless/core/aws_connection.py
rastless/core/cog.py
rastless/core/colormap.py
rastless/core/s3.py
rastless/core/schemas.py
rastless/core/utils.py
rastless/core/validate.py
rastless/custom_exceptions.py
rastless/db/__init__.py
rastless/db/base.py
rastless/db/handler.py
rastless/db/models.py
rastless/main.py
rastless/settings.py
rastless_cli-1.12.0.dist-info/METADATA
rastless_cli-1.12.0.dist-info/WHEEL
rastless_cli-1.12.0.dist-info/entry_points.txt
rastless_cli-1.12.0.dist-info/RECORD
