Metadata-Version: 2.4
Name: rastless-cli
Version: 1.12.0
Summary: A cli for managing data and user access for the cloud application rastless
Author: Marcel Siegmann
Author-email: siegmann@eomap.de
Requires-Python: >=3.10,<4.0
Classifier: Programming Language :: Python :: 3
Classifier: Programming Language :: Python :: 3.10
Classifier: Programming Language :: Python :: 3.11
Classifier: Programming Language :: Python :: 3.12
Classifier: Programming Language :: Python :: 3.13
Classifier: Programming Language :: Python :: 3.14
Requires-Dist: boto3 (>=1.28.69,<2.0.0)
Requires-Dist: click (>=8.1.7,<9.0.0)
Requires-Dist: moto (>=5.0.21,<6.0.0)
Requires-Dist: pydantic (>=2.10.2,<3.0.0)
Requires-Dist: rasterio (>=1.4.2,<2.0.0)
Requires-Dist: rio-cogeo (>=5.3.3,<6.0.0)
Requires-Dist: simplejson (>=3.19.1,<4.0.0)
